changtianml/__init__.cp38-win_amd64.pyd
changtianml/changtianml.cp38-win_amd64.pyd
changtianml/delete_c.cp38-win_amd64.pyd
changtianml/linux_auto_gen_whl.cp38-win_amd64.pyd
changtianml/name2features.cp38-win_amd64.pyd
changtianml/setup.cp38-win_amd64.pyd
changtianml/test.cp38-win_amd64.pyd
changtianml/version.cp38-win_amd64.pyd
changtianml/windows_auto_gen_whl.cp38-win_amd64.pyd
changtianml/module/automl/flaml/__init__.cp38-win_amd64.pyd
changtianml/module/automl/flaml/flaml_tuner.cp38-win_amd64.pyd
changtianml/module/automl/flaml/flaml_utils.cp38-win_amd64.pyd
changtianml/module/common/__init__.cp38-win_amd64.pyd
changtianml/module/common/task_config.cp38-win_amd64.pyd
changtianml/module/dataprocess/__init__.cp38-win_amd64.pyd
changtianml/module/dataprocess/data_process.cp38-win_amd64.pyd
changtianml/module/util/__init__.cp38-win_amd64.pyd
changtianml/module/util/report.cp38-win_amd64.pyd
changtianml/module/util/yaml_parser.cp38-win_amd64.pyd
changtianml-0.2.13.dist-info/METADATA
changtianml-0.2.13.dist-info/WHEEL
changtianml-0.2.13.dist-info/top_level.txt
changtianml-0.2.13.dist-info/RECORD
