Metadata-Version: 2.1
Name: changtianml
Version: 0.2.13
Requires-Python: >=3.8
Requires-Dist: catboost==1.2.2
Requires-Dist: FLAML==2.1.1
Requires-Dist: lightgbm==3.3.5
Requires-Dist: numpy==1.23.5
Requires-Dist: pandas==1.5.3
Requires-Dist: scikit-learn==1.2.2
Requires-Dist: xgboost==2.0.1
Requires-Dist: PyYAML==6.0
Requires-Dist: seaborn==0.13.0
Requires-Dist: requests>=2.31.0
Requires-Dist: shap>=0.46.0
